<?xml version="1.0" encoding="UTF-8"?>
<!DOCTYPE mapper PUBLIC "-//mybatis.org//DTD Mapper 3.0//EN" "http://mybatis.org/dtd/mybatis-3-mapper.dtd">
<mapper namespace="com.zyt.heima.dao.BlogDao">
  <resultMap id="BaseResultMap" type="com.zyt.heima.entity.Blog">
    <!--
      WARNING - @mbg.generated
      This element is automatically generated by MyBatis Generator, do not modify.
      This element was generated on Sat Sep 28 15:20:08 CST 2019.
    -->
    <id column="blogId" jdbcType="VARCHAR" property="blogid" />
    <result column="createTime" jdbcType="TIMESTAMP" property="createtime" />
    <result column="blogtag" jdbcType="VARCHAR" property="blogtag" />
    <result column="blogTitle" jdbcType="VARCHAR" property="blogtitle" />
    <result column="readnum" jdbcType="INTEGER" property="readnum" />
    <result column="goodnum" jdbcType="INTEGER" property="goodnum" />
    <result column="userId" jdbcType="VARCHAR" property="userid" />
  </resultMap>
  <resultMap extends="BaseResultMap" id="ResultMapWithBLOBs" type="com.zyt.heima.entity.Blog">
    <!--
      WARNING - @mbg.generated
      This element is automatically generated by MyBatis Generator, do not modify.
      This element was generated on Sat Sep 28 15:20:08 CST 2019.
    -->
    <result column="blogText" jdbcType="LONGVARCHAR" property="blogtext" />
  </resultMap>
  <sql id="Example_Where_Clause">
    <!--
      WARNING - @mbg.generated
      This element is automatically generated by MyBatis Generator, do not modify.
      This element was generated on Sat Sep 28 15:20:08 CST 2019.
    -->
    <where>
      <foreach collection="oredCriteria" item="criteria" separator="or">
        <if test="criteria.valid">
          <trim prefix="(" prefixOverrides="and" suffix=")">
            <foreach collection="criteria.criteria" item="criterion">
              <choose>
                <when test="criterion.noValue">
                  and ${criterion.condition}
                </when>
                <when test="criterion.singleValue">
                  and ${criterion.condition} #{criterion.value}
                </when>
                <when test="criterion.betweenValue">
                  and ${criterion.condition} #{criterion.value} and #{criterion.secondValue}
                </when>
                <when test="criterion.listValue">
                  and ${criterion.condition}
                  <foreach close=")" collection="criterion.value" item="listItem" open="(" separator=",">
                    #{listItem}
                  </foreach>
                </when>
              </choose>
            </foreach>
          </trim>
        </if>
      </foreach>
    </where>
  </sql>
  <sql id="Update_By_Example_Where_Clause">
    <!--
      WARNING - @mbg.generated
      This element is automatically generated by MyBatis Generator, do not modify.
      This element was generated on Sat Sep 28 15:20:08 CST 2019.
    -->
    <where>
      <foreach collection="example.oredCriteria" item="criteria" separator="or">
        <if test="criteria.valid">
          <trim prefix="(" prefixOverrides="and" suffix=")">
            <foreach collection="criteria.criteria" item="criterion">
              <choose>
                <when test="criterion.noValue">
                  and ${criterion.condition}
                </when>
                <when test="criterion.singleValue">
                  and ${criterion.condition} #{criterion.value}
                </when>
                <when test="criterion.betweenValue">
                  and ${criterion.condition} #{criterion.value} and #{criterion.secondValue}
                </when>
                <when test="criterion.listValue">
                  and ${criterion.condition}
                  <foreach close=")" collection="criterion.value" item="listItem" open="(" separator=",">
                    #{listItem}
                  </foreach>
                </when>
              </choose>
            </foreach>
          </trim>
        </if>
      </foreach>
    </where>
  </sql>
  <sql id="Base_Column_List">
    <!--
      WARNING - @mbg.generated
      This element is automatically generated by MyBatis Generator, do not modify.
      This element was generated on Sat Sep 28 15:20:08 CST 2019.
    -->
    blogId, createTime, blogtag, blogTitle, readnum, goodnum, userId
  </sql>
  <sql id="Blob_Column_List">
    <!--
      WARNING - @mbg.generated
      This element is automatically generated by MyBatis Generator, do not modify.
      This element was generated on Sat Sep 28 15:20:08 CST 2019.
    -->
    blogText
  </sql>
  <select id="selectByExampleWithBLOBs" parameterType="com.zyt.heima.entity.BlogExample" resultMap="ResultMapWithBLOBs">
    <!--
      WARNING - @mbg.generated
      This element is automatically generated by MyBatis Generator, do not modify.
      This element was generated on Sat Sep 28 15:20:08 CST 2019.
    -->
    select
    <if test="distinct">
      distinct
    </if>
    <include refid="Base_Column_List" />
    ,
    <include refid="Blob_Column_List" />
    from blog
    <if test="_parameter != null">
      <include refid="Example_Where_Clause" />
    </if>
    <if test="orderByClause != null">
      order by ${orderByClause}
    </if>
  </select>
  <select id="selectByExample" parameterType="com.zyt.heima.entity.BlogExample" resultMap="BaseResultMap">
    <!--
      WARNING - @mbg.generated
      This element is automatically generated by MyBatis Generator, do not modify.
      This element was generated on Sat Sep 28 15:20:08 CST 2019.
    -->
    select
    <if test="distinct">
      distinct
    </if>
    <include refid="Base_Column_List" />
    from blog
    <if test="_parameter != null">
      <include refid="Example_Where_Clause" />
    </if>
    <if test="orderByClause != null">
      order by ${orderByClause}
    </if>
  </select>
  <select id="selectByPrimaryKey" parameterType="java.lang.String" resultMap="ResultMapWithBLOBs">
    <!--
      WARNING - @mbg.generated
      This element is automatically generated by MyBatis Generator, do not modify.
      This element was generated on Sat Sep 28 15:20:08 CST 2019.
    -->
    select 
    <include refid="Base_Column_List" />
    ,
    <include refid="Blob_Column_List" />
    from blog
    where blogId = #{blogid,jdbcType=VARCHAR}
  </select>
  <delete id="deleteByPrimaryKey" parameterType="java.lang.String">
    <!--
      WARNING - @mbg.generated
      This element is automatically generated by MyBatis Generator, do not modify.
      This element was generated on Sat Sep 28 15:20:08 CST 2019.
    -->
    delete from blog
    where blogId = #{blogid,jdbcType=VARCHAR}
  </delete>
  <delete id="deleteByExample" parameterType="com.zyt.heima.entity.BlogExample">
    <!--
      WARNING - @mbg.generated
      This element is automatically generated by MyBatis Generator, do not modify.
      This element was generated on Sat Sep 28 15:20:08 CST 2019.
    -->
    delete from blog
    <if test="_parameter != null">
      <include refid="Example_Where_Clause" />
    </if>
  </delete>
  <insert id="insert" parameterType="com.zyt.heima.entity.Blog">
    <!--
      WARNING - @mbg.generated
      This element is automatically generated by MyBatis Generator, do not modify.
      This element was generated on Sat Sep 28 15:20:08 CST 2019.
    -->
    insert into blog (blogId, createTime, blogtag, 
      blogTitle, readnum, goodnum, 
      userId, blogText)
    values (#{blogid,jdbcType=VARCHAR}, #{createtime,jdbcType=TIMESTAMP}, #{blogtag,jdbcType=VARCHAR}, 
      #{blogtitle,jdbcType=VARCHAR}, #{readnum,jdbcType=INTEGER}, #{goodnum,jdbcType=INTEGER}, 
      #{userid,jdbcType=VARCHAR}, #{blogtext,jdbcType=LONGVARCHAR})
  </insert>
  <insert id="insertSelective" parameterType="com.zyt.heima.entity.Blog">
    <!--
      WARNING - @mbg.generated
      This element is automatically generated by MyBatis Generator, do not modify.
      This element was generated on Sat Sep 28 15:20:08 CST 2019.
    -->
    insert into blog
    <trim prefix="(" suffix=")" suffixOverrides=",">
      <if test="blogid != null">
        blogId,
      </if>
      <if test="createtime != null">
        createTime,
      </if>
      <if test="blogtag != null">
        blogtag,
      </if>
      <if test="blogtitle != null">
        blogTitle,
      </if>
      <if test="readnum != null">
        readnum,
      </if>
      <if test="goodnum != null">
        goodnum,
      </if>
      <if test="userid != null">
        userId,
      </if>
      <if test="blogtext != null">
        blogText,
      </if>
    </trim>
    <trim prefix="values (" suffix=")" suffixOverrides=",">
      <if test="blogid != null">
        #{blogid,jdbcType=VARCHAR},
      </if>
      <if test="createtime != null">
        #{createtime,jdbcType=TIMESTAMP},
      </if>
      <if test="blogtag != null">
        #{blogtag,jdbcType=VARCHAR},
      </if>
      <if test="blogtitle != null">
        #{blogtitle,jdbcType=VARCHAR},
      </if>
      <if test="readnum != null">
        #{readnum,jdbcType=INTEGER},
      </if>
      <if test="goodnum != null">
        #{goodnum,jdbcType=INTEGER},
      </if>
      <if test="userid != null">
        #{userid,jdbcType=VARCHAR},
      </if>
      <if test="blogtext != null">
        #{blogtext,jdbcType=LONGVARCHAR},
      </if>
    </trim>
  </insert>
  <select id="countByExample" parameterType="com.zyt.heima.entity.BlogExample" resultType="java.lang.Long">
    <!--
      WARNING - @mbg.generated
      This element is automatically generated by MyBatis Generator, do not modify.
      This element was generated on Sat Sep 28 15:20:08 CST 2019.
    -->
    select count(*) from blog
    <if test="_parameter != null">
      <include refid="Example_Where_Clause" />
    </if>
  </select>
  <update id="updateByExampleSelective" parameterType="map">
    <!--
      WARNING - @mbg.generated
      This element is automatically generated by MyBatis Generator, do not modify.
      This element was generated on Sat Sep 28 15:20:08 CST 2019.
    -->
    update blog
    <set>
      <if test="record.blogid != null">
        blogId = #{record.blogid,jdbcType=VARCHAR},
      </if>
      <if test="record.createtime != null">
        createTime = #{record.createtime,jdbcType=TIMESTAMP},
      </if>
      <if test="record.blogtag != null">
        blogtag = #{record.blogtag,jdbcType=VARCHAR},
      </if>
      <if test="record.blogtitle != null">
        blogTitle = #{record.blogtitle,jdbcType=VARCHAR},
      </if>
      <if test="record.readnum != null">
        readnum = #{record.readnum,jdbcType=INTEGER},
      </if>
      <if test="record.goodnum != null">
        goodnum = #{record.goodnum,jdbcType=INTEGER},
      </if>
      <if test="record.userid != null">
        userId = #{record.userid,jdbcType=VARCHAR},
      </if>
      <if test="record.blogtext != null">
        blogText = #{record.blogtext,jdbcType=LONGVARCHAR},
      </if>
    </set>
    <if test="_parameter != null">
      <include refid="Update_By_Example_Where_Clause" />
    </if>
  </update>
  <update id="updateByExampleWithBLOBs" parameterType="map">
    <!--
      WARNING - @mbg.generated
      This element is automatically generated by MyBatis Generator, do not modify.
      This element was generated on Sat Sep 28 15:20:08 CST 2019.
    -->
    update blog
    set blogId = #{record.blogid,jdbcType=VARCHAR},
      createTime = #{record.createtime,jdbcType=TIMESTAMP},
      blogtag = #{record.blogtag,jdbcType=VARCHAR},
      blogTitle = #{record.blogtitle,jdbcType=VARCHAR},
      readnum = #{record.readnum,jdbcType=INTEGER},
      goodnum = #{record.goodnum,jdbcType=INTEGER},
      userId = #{record.userid,jdbcType=VARCHAR},
      blogText = #{record.blogtext,jdbcType=LONGVARCHAR}
    <if test="_parameter != null">
      <include refid="Update_By_Example_Where_Clause" />
    </if>
  </update>
  <update id="updateByExample" parameterType="map">
    <!--
      WARNING - @mbg.generated
      This element is automatically generated by MyBatis Generator, do not modify.
      This element was generated on Sat Sep 28 15:20:08 CST 2019.
    -->
    update blog
    set blogId = #{record.blogid,jdbcType=VARCHAR},
      createTime = #{record.createtime,jdbcType=TIMESTAMP},
      blogtag = #{record.blogtag,jdbcType=VARCHAR},
      blogTitle = #{record.blogtitle,jdbcType=VARCHAR},
      readnum = #{record.readnum,jdbcType=INTEGER},
      goodnum = #{record.goodnum,jdbcType=INTEGER},
      userId = #{record.userid,jdbcType=VARCHAR}
    <if test="_parameter != null">
      <include refid="Update_By_Example_Where_Clause" />
    </if>
  </update>
  <update id="updateByPrimaryKeySelective" parameterType="com.zyt.heima.entity.Blog">
    <!--
      WARNING - @mbg.generated
      This element is automatically generated by MyBatis Generator, do not modify.
      This element was generated on Sat Sep 28 15:20:08 CST 2019.
    -->
    update blog
    <set>
      <if test="createtime != null">
        createTime = #{createtime,jdbcType=TIMESTAMP},
      </if>
      <if test="blogtag != null">
        blogtag = #{blogtag,jdbcType=VARCHAR},
      </if>
      <if test="blogtitle != null">
        blogTitle = #{blogtitle,jdbcType=VARCHAR},
      </if>
      <if test="readnum != null">
        readnum = #{readnum,jdbcType=INTEGER},
      </if>
      <if test="goodnum != null">
        goodnum = #{goodnum,jdbcType=INTEGER},
      </if>
      <if test="userid != null">
        userId = #{userid,jdbcType=VARCHAR},
      </if>
      <if test="blogtext != null">
        blogText = #{blogtext,jdbcType=LONGVARCHAR},
      </if>
    </set>
    where blogId = #{blogid,jdbcType=VARCHAR}
  </update>
  <update id="updateByPrimaryKeyWithBLOBs" parameterType="com.zyt.heima.entity.Blog">
    <!--
      WARNING - @mbg.generated
      This element is automatically generated by MyBatis Generator, do not modify.
      This element was generated on Sat Sep 28 15:20:08 CST 2019.
    -->
    update blog
    set createTime = #{createtime,jdbcType=TIMESTAMP},
      blogtag = #{blogtag,jdbcType=VARCHAR},
      blogTitle = #{blogtitle,jdbcType=VARCHAR},
      readnum = #{readnum,jdbcType=INTEGER},
      goodnum = #{goodnum,jdbcType=INTEGER},
      userId = #{userid,jdbcType=VARCHAR},
      blogText = #{blogtext,jdbcType=LONGVARCHAR}
    where blogId = #{blogid,jdbcType=VARCHAR}
  </update>
  <update id="updateByPrimaryKey" parameterType="com.zyt.heima.entity.Blog">
    <!--
      WARNING - @mbg.generated
      This element is automatically generated by MyBatis Generator, do not modify.
      This element was generated on Sat Sep 28 15:20:08 CST 2019.
    -->
    update blog
    set createTime = #{createtime,jdbcType=TIMESTAMP},
      blogtag = #{blogtag,jdbcType=VARCHAR},
      blogTitle = #{blogtitle,jdbcType=VARCHAR},
      readnum = #{readnum,jdbcType=INTEGER},
      goodnum = #{goodnum,jdbcType=INTEGER},
      userId = #{userid,jdbcType=VARCHAR}
    where blogId = #{blogid,jdbcType=VARCHAR}
  </update>
</mapper>